{
  "directories": {
    "name": "Home",
    "path": "/fa/id_en/index.html",
    "child": [
      {
        "name": "Products",
        "path": "/fa/id_en/products/index.html",
        "child": [
          {
            "name": "Low-voltage Circuit Breakers",
            "path": "/fa/id_en/products/lvd/lvcb/index.html",
            "child": [
				{
					"name": "Circuit Breakers for Equipment",
					"path": "/fa/id_en/products/lvd/lvcb/pmerit/cbe/index.html"
				}
            ]
          }
        ]
      }
    ]
  },
  "layerNav": {
    "name": "Circuit Breakers for Equipment",
    "path": "/fa/id_en/products/lvd/lvcb/pmerit/cbe/index.html",
    "firstLayer": [
      {
        "name": "Circuit Protectors",
        "path": "/fa/id_en/products/lvd/lvcb/pmerit/cbe/index.html",
        "secondLayer": [
        {
          "name": "Features",
          "path": "/fa/id_en/products/lvd/lvcb/pmerit/cbe/index.html"
        },
        {
          "name": "Product Lineup",
          "path": "/fa/id_en/products/lvd/lvcb/pmerit/cbe/index_2.html"
        }
        ]
     },
      {
        "name": "Safety Breaker-Type Earth Leakage Circuit Breakers",
        "path": "/fa/id_en/products/lvd/lvcb/pmerit/cbe/index_3.html",
        "secondLayer": [
        {
          "name": "Features",
          "path": "/fa/id_en/products/lvd/lvcb/pmerit/cbe/index_3.html"
        }
        ]
      }
    ]
  },
"switchNav": {
	"name": "Circuit Breakers for Equipment",
	"path": "/fa/id_en/products/lvd/lvcb/items/cbe/index.html",
	"child": [
		{
			"group": "Circuit Breakers for Equipment",
			"name": "Circuit Breakers for Equipment",
			"feature": "/fa/id_en/products/lvd/lvcb/pmerit/cbe/index.html",
			"spec": "https://www.mitsubishielectric.com/fa/id_en/products/faspec/search.page?kisyu=/lvcb&current=CBE",
			"standard": "https://www.mitsubishielectric.com/fa/products/standard/SearchServlet.page?kisyu=/lvcb&current=CBE",
			"discon": "",
            "return": {
                "name": "Circuit Breakers for Equipment",
                "path": "/fa/id_en/products/lvd/lvcb/items/cbe/index.html"
			}
		}
	]
}
}
  